pget/__init__.py
pget/bin.py
pget/chunk.py
pget/down.py
pget/log.py
pget/term.py
PGet-0.5.1.dist-info/LICENSE
PGet-0.5.1.dist-info/METADATA
PGet-0.5.1.dist-info/WHEEL
PGet-0.5.1.dist-info/entry_points.txt
PGet-0.5.1.dist-info/top_level.txt
PGet-0.5.1.dist-info/RECORD
